bytesclient/__init__.py
bytesclient/application.py
bytesclient/application_async.py
byteshost_client-0.1.1.dist-info/METADATA
byteshost_client-0.1.1.dist-info/WHEEL
byteshost_client-0.1.1.dist-info/top_level.txt
byteshost_client-0.1.1.dist-info/RECORD
