Metadata-Version: 2.4
Name: byteshost-client
Version: 0.1.1
Summary: API wrapper for communicating with the main application
Author-email: Your Name <you@example.com>
License-Expression: MIT
Project-URL: Homepage, https://www.youtube.com/watch?v=dQw4w9WgXcQ
Project-URL: Bug Tracker, https://www.youtube.com/watch?v=dQw4w9WgXcQ
Requires-Python: >=3.8
